_garnet/__init__.py
_garnet/client.py
_garnet/concurrency.py
_garnet/events/__init__.py
_garnet/events/filter.py
_garnet/events/handler.py
_garnet/events/router.py
_garnet/events/user_cage.py
_garnet/filters/__init__.py
_garnet/filters/cb_query.py
_garnet/filters/file_ext.py
_garnet/filters/state.py
_garnet/filters/text.py
_garnet/helpers/__init__.py
_garnet/helpers/ctx.py
_garnet/helpers/var.py
_garnet/loggers.py
_garnet/patched_events.py
_garnet/runner.py
_garnet/storages/__init__.py
_garnet/storages/base.py
_garnet/storages/dict.py
_garnet/storages/json.py
_garnet/storages/typedef.py
_garnet/vars/__init__.py
_garnet/vars/fsm.py
_garnet/vars/handler.py
_garnet/vars/query.py
_garnet/vars/user_and_chat.py
garnet/__init__.py
garnet/concurrency.py
garnet/ctx.py
garnet/events.py
garnet/filters/__init__.py
garnet/filters/group.py
garnet/handler.py
garnet/runner.py
garnet/storages.py
telegram_garnet-0.5.2.dist-info/LICENSE
telegram_garnet-0.5.2.dist-info/WHEEL
telegram_garnet-0.5.2.dist-info/METADATA
telegram_garnet-0.5.2.dist-info/RECORD
