Metadata-Version: 2.1
Name: telegram-garnet
Version: 0.5.2
Summary: garnet - cool add-on for Telethon
Home-page: https://github.com/uwinx/garnet
Keywords: telegram,telethon,telegram-bot,bot
Author: Martin Winks
Author-email: cat@snejugal.ru
Requires-Python: >=3.8,<4.0
Classifier: Framework :: AsyncIO
Classifier: Intended Audience :: Developers
Classifier: Programming Language :: Python :: 3
Classifier: Programming Language :: Python :: 3.8
Classifier: Programming Language :: Python :: 3.9
Requires-Dist: Telethon (>=1.10.8,<2.0.0)
Project-URL: Repository, https://github.com/uwinx/garnet
